py_yfinance/__init__.py
py_yfinance/cli.py
py_yfinance/py.typed
py_yfinance/source.py
py_yfinance-0.1.1.dist-info/METADATA
py_yfinance-0.1.1.dist-info/WHEEL
py_yfinance-0.1.1.dist-info/entry_points.txt
py_yfinance-0.1.1.dist-info/licenses/LICENSE
py_yfinance-0.1.1.dist-info/RECORD
