Metadata-Version: 2.4
Name: py-yfinance
Version: 0.1.1
Summary: A structured Python interface for retrieving and validating market data using yfinance
Project-URL: Homepage, https://github.com/romamo/py-yfinance
Project-URL: Repository, https://github.com/romamo/py-yfinance
Project-URL: Issues, https://github.com/romamo/py-yfinance/issues
Author-email: Roman Medvedev <pypi@romavm.dev>
License: MIT
License-File: LICENSE
Classifier: Development Status :: 3 - Alpha
Classifier: Intended Audience :: Developers
Classifier: License :: OSI Approved :: MIT License
Classifier: Programming Language :: Python :: 3
Classifier: Programming Language :: Python :: 3.10
Classifier: Programming Language :: Python :: 3.11
Classifier: Programming Language :: Python :: 3.12
Classifier: Programming Language :: Python :: 3.13
Classifier: Programming Language :: Python :: 3.14
Requires-Python: >=3.10
Requires-Dist: pycountry>=24.6.1
Requires-Dist: pydantic-market-data>=0.1.0
Requires-Dist: yfinance>=1.0
Provides-Extra: cli
Requires-Dist: typer; extra == 'cli'
